flex_version
